ebryx/__init__.py
ebryx/crypto/__init__.py
ebryx/crypto/__main__.py
ebryx/crypto/_crypto.py
ebryx/crypto/crypto.py
ebryx/crypto/main.py
ebryx-0.4.1.dist-info/LICENSE
ebryx-0.4.1.dist-info/METADATA
ebryx-0.4.1.dist-info/WHEEL
ebryx-0.4.1.dist-info/entry_points.txt
ebryx-0.4.1.dist-info/top_level.txt
ebryx-0.4.1.dist-info/RECORD
