Metadata-Version: 2.1
Name: ebryx
Version: 0.4.1
Summary: Official library for Ebryx LLC.
Home-page: https://github.com/EbryxLabs/ebryx
Author: Rana Awais
Author-email: rana.awais@ebryx.com
License: UNKNOWN
Platform: UNKNOWN
Classifier: Programming Language :: Python :: 3
Classifier: License :: OSI Approved :: MIT License
Classifier: Operating System :: OS Independent
Requires-Dist: cryptography
